MANIFEST.in
README.md
ez_setup.py
setup.py
metaphor/__init__.py
metaphor/version_client.py
metaphor/client_doc/build/html/.buildinfo
metaphor/client_doc/build/html/api.html
metaphor/client_doc/build/html/genindex.html
metaphor/client_doc/build/html/metaphor_client.html
metaphor/client_doc/build/html/model.html
metaphor/client_doc/build/html/objects.inv
metaphor/client_doc/build/html/py-modindex.html
metaphor/client_doc/build/html/search.html
metaphor/client_doc/build/html/searchindex.js
metaphor/client_doc/build/html/.doctrees/api.doctree
metaphor/client_doc/build/html/.doctrees/environment.pickle
metaphor/client_doc/build/html/.doctrees/metaphor_client.doctree
metaphor/client_doc/build/html/.doctrees/model.doctree
metaphor/client_doc/build/html/_modules/api_client.html
metaphor/client_doc/build/html/_modules/client_toolbox.html
metaphor/client_doc/build/html/_modules/index.html
metaphor/client_doc/build/html/_modules/meta_client/api_client.html
metaphor/client_doc/build/html/_modules/meta_client/client_toolbox.html
metaphor/client_doc/build/html/_modules/model/model.html
metaphor/client_doc/build/html/_sources/api.rst.txt
metaphor/client_doc/build/html/_sources/metaphor_client.rst.txt
metaphor/client_doc/build/html/_sources/model.rst.txt
metaphor/client_doc/build/html/_static/background_b01.png
metaphor/client_doc/build/html/_static/basic.css
metaphor/client_doc/build/html/_static/bizstyle.css
metaphor/client_doc/build/html/_static/bizstyle.js
metaphor/client_doc/build/html/_static/css3-mediaqueries.js
metaphor/client_doc/build/html/_static/css3-mediaqueries_src.js
metaphor/client_doc/build/html/_static/doctools.js
metaphor/client_doc/build/html/_static/documentation_options.js
metaphor/client_doc/build/html/_static/file.png
metaphor/client_doc/build/html/_static/jquery-3.2.1.js
metaphor/client_doc/build/html/_static/jquery.js
metaphor/client_doc/build/html/_static/language_data.js
metaphor/client_doc/build/html/_static/minus.png
metaphor_client.egg-info/PKG-INFO
metaphor_client.egg-info/SOURCES.txt
metaphor_client.egg-info/dependency_links.txt
metaphor_client.egg-info/not-zip-safe
metaphor_client.egg-info/top_level.txt